datamation/__init__.py
datamation/db/__init__.py
datamation/db/api.py
datamation/db/cache.py
datamation/db/engine/__init__.py
datamation/db/engine/mysql.py
datamation/db/engine/oracle.py
datamation/db/engine/schema.py
datamation/db/extend/__init__.py
datamation/db/extend/clickhouse.py
datamation/db/extend/mysql.py
datamation/db/extend/pgsql.py
datamation/db/ldr.py
datamation/db/source.py
datamation/db/sql.py
datamation/db/sync.py
datamation/db/table.py
datamation/db/uldr.py
datamation/db/utils/__init__.py
datamation/db/utils/general.py
datamation/db/utils/sqldata.py
datamation/db/utils/sqldb.py
datamation/db/utils/sqltab.py
datamation/db/utils/transform.py
datamation/email/__init__.py
datamation/email/api.py
datamation/email/exchange.py
datamation/email/mail.py
datamation/email/temp.py
datamation/email/tool.py
datamation/etl/__init__.py
datamation/etl/api.py
datamation/etl/control_m.py
datamation/etl/kettle.py
datamation/etl/schemy.py
datamation/etl/template/ktr.xml
datamation/etl/tool.py
datamation/log.py
datamation/send/__init__.py
datamation/send/dingtalk.py
datamation/send/wechat.py
datamation/utils/__init__.py
datamation/utils/backup.py
datamation/utils/command.py
datamation/utils/style.py
datamation/web/__init__.py
datamation/web/sync_app.py
datamation-0.1.5.dist-info/METADATA
datamation-0.1.5.dist-info/WHEEL
datamation-0.1.5.dist-info/entry_points.txt
datamation-0.1.5.dist-info/RECORD
