Metadata-Version: 2.1
Name: datamation
Version: 0.1.5
Summary: Data information synchronization
License: BSD
Keywords: etl,synchronization
Author: lidaoran
Author-email: qianxuanyon@hotmail.com
Requires-Python: >=3.7,<4.0
Classifier: License :: Other/Proprietary License
Classifier: Programming Language :: Python :: 3
Classifier: Programming Language :: Python :: 3.7
Classifier: Programming Language :: Python :: 3.8
Classifier: Programming Language :: Python :: 3.9
Classifier: Programming Language :: Python :: 3.10
Classifier: Programming Language :: Python :: 3.11
Classifier: Programming Language :: Python :: 3.12
Classifier: Programming Language :: Python :: 3.13
Provides-Extra: kettle
Requires-Dist: SQLAlchemy
Requires-Dist: python-dateutil
Requires-Dist: requests
